emox/__init__.py
emox/main.py
emox/model_pickle.pkl
emox/word_index.pkl
emox-0.1.dist-info/METADATA
emox-0.1.dist-info/WHEEL
emox-0.1.dist-info/top_level.txt
emox-0.1.dist-info/RECORD
