Metadata-Version: 2.4
Name: emox
Version: 0.1
Requires-Dist: scipy==1.13.1
Requires-Dist: numpy==1.26.4
Requires-Dist: gensim==4.3.3
Requires-Dist: tensorflow==2.18.0
Dynamic: requires-dist
